DomRetryLibrary.py
domretrylibrary/__init__.py
domretrylibrary/ai_processor.py
domretrylibrary/core.py
domretrylibrary/keyword_handler.py
domretrylibrary/locator_manager.py
robotframework_domretrylibrary-4.0.1.dist-info/LICENSE
robotframework_domretrylibrary-4.0.1.dist-info/METADATA
robotframework_domretrylibrary-4.0.1.dist-info/WHEEL
robotframework_domretrylibrary-4.0.1.dist-info/top_level.txt
robotframework_domretrylibrary-4.0.1.dist-info/RECORD
