Metadata-Version: 2.1
Name: robotframework-domretrylibrary
Version: 4.0.1
Summary: AI-powered smart locator with retry functionality for Robot Framework using OpenAI
Home-page: https://github.com/plaushku/robotframework-domretrylibrary
Author: Kristijan Plaushku
Author-email: info@plaushkusolutions.com
License: UNKNOWN
Platform: UNKNOWN
Classifier: Framework :: Robot Framework
Classifier: Programming Language :: Python :: 3
Classifier: Programming Language :: Python :: 3.7
Classifier: Programming Language :: Python :: 3.8
Classifier: Programming Language :: Python :: 3.9
Classifier: License :: OSI Approved :: MIT License
Requires-Python: >=3.7
License-File: LICENSE
Requires-Dist: robotframework (>=4.0.0)
Requires-Dist: python-dotenv (>=0.19.0)
Requires-Dist: requests (>=2.25.0)
